snakemake_storage_plugin_dirac/__init__.py
snakemake_storage_plugin_dirac-0.1.0.dist-info/LICENSE
snakemake_storage_plugin_dirac-0.1.0.dist-info/METADATA
snakemake_storage_plugin_dirac-0.1.0.dist-info/WHEEL
snakemake_storage_plugin_dirac-0.1.0.dist-info/RECORD
