Metadata-Version: 2.3
Name: snakemake-storage-plugin-dirac
Version: 0.1.0
Summary: A Snakemake storage plugin for the DIRAC Data Management System (DMS).
License: MIT
Author: Jannis Speer
Author-email: jannis.speer@tutanota.com
Requires-Python: >=3.11,<4.0
Classifier: License :: OSI Approved :: MIT License
Classifier: Programming Language :: Python :: 3
Classifier: Programming Language :: Python :: 3.11
Classifier: Programming Language :: Python :: 3.12
Classifier: Programming Language :: Python :: 3.13
Requires-Dist: DIRAC (>=8.0,<10.0)
Requires-Dist: snakemake-interface-common (>=1.17.3,<2.0.0)
Requires-Dist: snakemake-interface-storage-plugins (>=3.3,<5.0)
Project-URL: Documentation, https://snakemake.github.io/snakemake-plugin-catalog/plugins/storage/dirac.html
Project-URL: Repository, https://github.com/jannisspeer/snakemake-storage-plugin-dirac
